n2_fit/__init__.py
n2_fit/bluesky_interface.py
n2_fit/create_tables.py
n2_fit/fit.py
n2_fit/helper_functions.py
n2_fit/models.py
n2_fit/n2_peaks_parameters.py
n2_fit-0.0.47.dist-info/METADATA
n2_fit-0.0.47.dist-info/WHEEL
n2_fit-0.0.47.dist-info/top_level.txt
n2_fit-0.0.47.dist-info/RECORD
